{"activityId":5390735141,"activityUUID":{"uuid":"353060c8-8752-415b-b01c-05325ac5ca2d"},"activityName":"Anne Arundel County Cycling","userProfileId":2974142,"isMultiSportParent":false,"activityTypeDTO":{"typeId":2,"typeKey":"cycling","parentTypeId":17,"sortOrder":8,"isHidden":false,"restricted":false},"eventTypeDTO":{"typeId":9,"typeKey":"uncategorized","sortOrder":10},"accessControlRuleDTO":{"typeId":3,"typeKey":"subscribers"},"timeZoneUnitDTO":{"unitId":149,"unitKey":"America/New_York","factor":0.0,"timeZone":"America/New_York"},"metadataDTO":{"isOriginal":true,"deviceApplicationInstallationId":870190,"agentApplicationInstallationId":null,"agentString":null,"fileFormat":{"formatId":7,"formatKey":"fit"},"associatedCourseId":null,"lastUpdateDate":"2020-08-15T19:28:16.0","uploadedDate":"2020-08-15T19:28:16.0","videoUrl":null,"hasPolyline":true,"hasChartData":true,"hasHrTimeInZones":true,"hasPowerTimeInZones":false,"userInfoDto":{"userProfilePk":2974142,"displayname":"sriperinkulam","fullname":"Srikanth Perinkulam","profileImageUrlLarge":null,"profileImageUrlMedium":"https://s3.amazonaws.com/garmin-connect-prod/profile_images/16754a02-53d0-455b-9719-eb712701b621-2974142.png","profileImageUrlSmall":"https://s3.amazonaws.com/garmin-connect-prod/profile_images/6d79cf08-9cd4-4c3b-9a7f-ce21187eb8d6-2974142.png","userPro":false},"chartAvailability":{},"childIds":[],"childActivityTypes":[],"sensors":[],"activityImages":[],"manufacturer":"GARMIN","diveNumber":null,"lapCount":3,"associatedWorkoutId":null,"isAtpActivity":null,"deviceMetaDataDTO":{"deviceId":"3317660550","deviceTypePk":31614,"deviceVersionPk":870190},"hasIntensityIntervals":false,"hasSplits":false,"manualActivity":false,"autoCalcCalories":false,"favorite":false,"trimmed":false,"personalRecord":false,"gcj02":false,"elevationCorrected":true},"summaryDTO":{"startTimeLocal":"2020-08-09T15:19:00.0","startTimeGMT":"2020-08-09T19:19:00.0","startLatitude":39.16101546026766,"startLongitude":-76.66242700070143,"distance":17215.25,"duration":4390.434,"movingDuration":3743.0,"elapsedDuration":4390.434,"elevationGain":83.13,"elevationLoss":81.13,"maxElevation":62.37,"minElevation":18.0,"averageSpeed":3.9210000038146973,"averageMovingSpeed":4.599318728292813,"maxSpeed":10.852000236511229,"calories":721.0,"averageHR":149.0,"maxHR":190.0,"trainingEffect":4.199999809265137,"endLatitude":39.162620175629854,"endLongitude":-76.6633260436356,"maxVerticalSpeed":0.46413326263427734,"minActivityLapDuration":275.2},"locationName":"Anne Arundel County"}