{"activityId":11109504791,"activityUUID":{"uuid":"1d9ba1f2-9a03-402f-8ff5-2903bad28739"},"activityName":"Cuauhtémoc Cycling","userProfileId":2974142,"isMultiSportParent":false,"activityTypeDTO":{"typeId":2,"typeKey":"cycling","parentTypeId":17,"isHidden":false,"restricted":false,"trimmable":true},"eventTypeDTO":{"typeId":9,"typeKey":"uncategorized","sortOrder":10},"accessControlRuleDTO":{"typeId":3,"typeKey":"subscribers"},"timeZoneUnitDTO":{"unitId":152,"unitKey":"America/Chicago","factor":0.0,"timeZone":"America/Chicago"},"metadataDTO":{"isOriginal":true,"deviceApplicationInstallationId":869340,"agentApplicationInstallationId":null,"agentString":null,"fileFormat":{"formatId":7,"formatKey":"fit"},"associatedCourseId":null,"lastUpdateDate":"2023-05-13T17:26:50.0","uploadedDate":"2023-05-13T17:26:50.0","videoUrl":null,"hasPolyline":true,"hasChartData":true,"hasHrTimeInZones":true,"hasPowerTimeInZones":false,"userInfoDto":{"userProfilePk":2974142,"displayname":"sriperinkulam","fullname":"Srikanth Perinkulam","profileImageUrlLarge":null,"profileImageUrlMedium":"https://s3.amazonaws.com/garmin-connect-prod/profile_images/16754a02-53d0-455b-9719-eb712701b621-2974142.png","profileImageUrlSmall":"https://s3.amazonaws.com/garmin-connect-prod/profile_images/6d79cf08-9cd4-4c3b-9a7f-ce21187eb8d6-2974142.png","userPro":false},"childIds":[],"childActivityTypes":[],"sensors":[],"activityImages":[],"manufacturer":"GARMIN","diveNumber":null,"lapCount":1,"associatedWorkoutId":null,"isAtpActivity":null,"deviceMetaDataDTO":{"deviceId":"3317660550","deviceTypePk":31614,"deviceVersionPk":869340},"hasIntensityIntervals":false,"hasSplits":false,"eBikeMaxAssistModes":null,"eBikeBatteryUsage":null,"eBikeBatteryRemaining":null,"eBikeAssistModeInfoDTOList":null,"calendarEventInfo":null,"trimmed":false,"manualActivity":false,"runPowerWindDataEnabled":null,"personalRecord":false,"gcj02":false,"autoCalcCalories":false,"favorite":false,"elevationCorrected":true},"summaryDTO":{"startTimeLocal":"2023-05-11T17:51:09.0","startTimeGMT":"2023-05-11T22:51:09.0","startLatitude":19.42911953665316,"startLongitude":-99.16541640646756,"distance":4885.5,"duration":1187.91,"movingDuration":1172.0,"elapsedDuration":1187.91,"elevationGain":68.74,"elevationLoss":56.62,"maxElevation":2295.96,"minElevation":2237.09,"averageSpeed":4.11299991607666,"averageMovingSpeed":4.168515358361775,"maxSpeed":7.837999820709229,"calories":186.0,"averageHR":157.0,"maxHR":175.0,"trainingEffect":3.5999999046325684,"endLatitude":19.435408897697926,"endLongitude":-99.19893731363118,"maxVerticalSpeed":2.83416748046875,"minActivityLapDuration":1187.91},"locationName":"Cuauhtémoc"}